sqlcritic/__init__.py
sqlcritic/action.py
sqlcritic/analyze.py
sqlcritic/collector.py
sqlcritic/comparison.py
sqlcritic/github.py
sqlcritic/notify.py
sqlcritic/storage.py
sqlcritic/trace.py
sqlcritic/utils.py
sqlcritic/database/__init__.py
sqlcritic/database/postgres.py
sqlcritic-0.3.0.dist-info/METADATA
sqlcritic-0.3.0.dist-info/WHEEL
sqlcritic-0.3.0.dist-info/top_level.txt
sqlcritic-0.3.0.dist-info/RECORD
