Metadata-Version: 2.1
Name: sqlcritic
Version: 0.3.0
Summary: Capture and analyze SQL queries made during a run of your app's test suite
Author-email: Scott Nelson <scott@scottnelson.co>
Requires-Python: >=3.9
Requires-Dist: boto3
Requires-Dist: opentelemetry-api >=1.11
Requires-Dist: opentelemetry-sdk >=1.11
Requires-Dist: PyGithub
Requires-Dist: psycopg2
Provides-Extra: dev
Requires-Dist: black ; extra == 'dev'
Requires-Dist: isort ; extra == 'dev'
Requires-Dist: pytest ; extra == 'dev'
Requires-Dist: pytest-cov ; extra == 'dev'
Requires-Dist: pytest-mock ; extra == 'dev'
Requires-Dist: vcrpy ; extra == 'dev'
Requires-Dist: mypy ; extra == 'dev'
Requires-Dist: types-python-dateutil ; extra == 'dev'
Requires-Dist: types-psycopg2 ; extra == 'dev'
Requires-Dist: types-boto3 ; extra == 'dev'
